<?xml version="1.0" encoding="UTF-8"?>
<ruleset name="Java Exception Handling Rules"
        xmlns="http://pmd.sourceforge.net/ruleset/2.0.0"
        xmlns:xsi="http://www.w3.org/2001/XMLSchema-instance"
        xsi:schemaLocation="http://pmd.sourceforge.net/ruleset/2.0.0 https://pmd.sourceforge.io/ruleset_2_0_0.xsd">

    <description>
        Rules which enforce proper exception handling.
    </description>

    <rule ref="category/java/bestpractices.xml/AvoidPrintStackTrace" />
    <rule ref="category/java/codestyle.xml/IdenticalCatchBranches" />
    <rule ref="category/java/design.xml/AvoidCatchingGenericException" />
    <rule ref="category/java/errorprone.xml/AvoidCatchingThrowable" />
    <rule ref="category/java/design.xml/AvoidRethrowingException" />
    <rule ref="category/java/design.xml/AvoidThrowingNewInstanceOfSameException" />
    <rule ref="category/java/design.xml/AvoidThrowingRawExceptionTypes" />
    <rule ref="category/java/design.xml/DoNotExtendJavaLangError" />
    <rule ref="category/java/errorprone.xml/DoNotExtendJavaLangThrowable" />
    <rule ref="category/java/errorprone.xml/AvoidCatchingNPE" />
    <rule ref="category/java/errorprone.xml/AvoidInstanceofChecksInCatchClause" />
    <rule ref="category/java/errorprone.xml/DoNotThrowExceptionInFinally" />
    <rule ref="category/java/errorprone.xml/EmptyCatchBlock" />

</ruleset>
